drf_spectacular_extensions/__init__.py
drf_spectacular_extensions/postprocessing_hooks.py
drf_spectacular_extensions-0.0.2.dist-info/LICENSE
drf_spectacular_extensions-0.0.2.dist-info/WHEEL
drf_spectacular_extensions-0.0.2.dist-info/METADATA
drf_spectacular_extensions-0.0.2.dist-info/RECORD
