Metadata-Version: 2.1
Name: drf_spectacular_extensions
Version: 0.0.2
Summary: Various JSON logging extensions for the DRF Spectacular
Home-page: https://github.com/vskrachkov/drf_spectacular_extensions
Author: Viacheslav Krachkov
Author-email: vskrachkov@gmail.com
Requires-Python: >=3.9
Classifier: License :: OSI Approved :: MIT License
Requires-Dist: drf-spectacular>=0.17.2
Requires-Dist: django>=3.2
Requires-Dist: djangorestframework>=3.10.0
